{"v":1,"id":["q11568","q696557","q189657","q65096742","q15933552"],"name":["Darwin","Bombing of Darwin","Kakadu National Park","Kakadu National Park","Australian Fossil Mammal Sites (Riversleigh / Naracoorte)"],"lat":[-12.4381,-12.475,-13.0055,-13.0055,-19.0833],"lon":[130.8411,130.85,132.5195,132.5195,138.7167],"year":[1869,1942,1979,1981,1994],"endYear":[null,null,null,null,null],"category":["city","battle","monument","monument","monument"],"notability":[132,26,66,0,6],"wiki":["Darwin, Northern Territory","","",null,""],"cell":["-2|13","-2|13","-2|13","-2|13","-2|13"]}