{"v":1,"id":["q486124","q3079892","q488278","q826083","q565661","q2300090","q81788","q514382"],"name":["Battle of Badr","Invasion of Banu Qaynuqa","Battle of Uhud","Battle of the Trench","Battle of Khaybar","Battle of Hunayn","Giza","Battle of al-Harrah"],"lat":[23.7333,24.4667,24.5033,24.4667,25.6986,22.9733,29.987,24.4667],"lon":[38.7667,39.6,39.6117,39.6,39.2925,38.8197,31.2118,39.6333],"year":[624,624,625,627,628,630,642,683],"endYear":[null,null,null,null,null,null,null,null],"category":["battle","battle","battle","battle","battle","battle","city","battle"],"notability":[80,19,64,55,41,36,114,18],"wiki":["","Siege of Banu Qaynuqa","","","","","","Battle of al-Harra"],"cell":["2|3","2|3","2|3","2|3","2|3","2|3","2|3","2|3"]}